LICENSE
auditless_solcx/__init__.py
auditless_solcx/main.py
auditless_py_solc_x-0.1.0.dist-info/LICENSE
auditless_py_solc_x-0.1.0.dist-info/WHEEL
auditless_py_solc_x-0.1.0.dist-info/METADATA
auditless_py_solc_x-0.1.0.dist-info/RECORD
