Metadata-Version: 2.1
Name: auditless-py-solc-x
Version: 0.1.0
Summary: py-solc-x wrapper for Auditless
Home-page: https://github.com/auditless/auditless-py-solc-x
License: MIT
Author: Peteris Erins
Author-email: peteris@auditless.com
Requires-Python: >=3.8,<4.0
Classifier: License :: OSI Approved :: MIT License
Classifier: Programming Language :: Python :: 3
Classifier: Programming Language :: Python :: 3.8
Classifier: Programming Language :: Python :: 3.9
Requires-Dist: py-solc-x (>=1.1.0,<2.0.0)
Project-URL: Repository, https://github.com/auditless/auditless-py-solc-x
